gecko/__init__.py
gecko/data.py
gecko/transform.py
gecko/utils.py
gecko_soho-0.0.8.dist-info/LICENSE
gecko_soho-0.0.8.dist-info/METADATA
gecko_soho-0.0.8.dist-info/WHEEL
gecko_soho-0.0.8.dist-info/top_level.txt
gecko_soho-0.0.8.dist-info/RECORD
