Metadata-Version: 2.1
Name: gecko-soho
Version: 0.0.8
Summary: Utility lib for the Sungrazer project.
Home-page: https://github.com/artkra/gecko
Author: Artem Krasnyi
Author-email: artkrasnyy@gmail.com
Classifier: Programming Language :: Python :: 3
Classifier: License :: OSI Approved :: GNU General Public License v2 (GPLv2)
Classifier: Operating System :: OS Independent
Requires-Python: >=3.9
License-File: LICENSE
Requires-Dist: numpy >=1.24.0
Requires-Dist: Pillow >=8.3.2
Requires-Dist: ipython ==7.34.0
Requires-Dist: ipython-genutils >=0.2.0
